tensorrt_lean_libs/__init__.py
tensorrt_lean_libs/libnvinfer_lean.so.10
tensorrt_lean_libs/libnvinfer_vc_plugin.so.10
tensorrt_lean_cu13_libs-10.15.1.29.dist-info/LICENSE.txt
tensorrt_lean_cu13_libs-10.15.1.29.dist-info/METADATA
tensorrt_lean_cu13_libs-10.15.1.29.dist-info/WHEEL
tensorrt_lean_cu13_libs-10.15.1.29.dist-info/top_level.txt
tensorrt_lean_cu13_libs-10.15.1.29.dist-info/zip-safe
tensorrt_lean_cu13_libs-10.15.1.29.dist-info/RECORD
